timecopilot/__init__.py
timecopilot/_cli.py
timecopilot/agent.py
timecopilot/forecaster.py
timecopilot/gift_eval/__init__.py
timecopilot/gift_eval/data.py
timecopilot/gift_eval/eval.py
timecopilot/gift_eval/gluonts_predictor.py
timecopilot/gift_eval/utils.py
timecopilot/models/__init__.py
timecopilot/models/ml.py
timecopilot/models/neural.py
timecopilot/models/prophet.py
timecopilot/models/stats.py
timecopilot/models/ensembles/__init__.py
timecopilot/models/ensembles/median.py
timecopilot/models/foundation/__init__.py
timecopilot/models/foundation/chronos.py
timecopilot/models/foundation/flowstate.py
timecopilot/models/foundation/moirai.py
timecopilot/models/foundation/sundial.py
timecopilot/models/foundation/tabpfn.py
timecopilot/models/foundation/timegpt.py
timecopilot/models/foundation/timesfm.py
timecopilot/models/foundation/tirex.py
timecopilot/models/foundation/toto.py
timecopilot/models/foundation/utils.py
timecopilot/models/utils/__init__.py
timecopilot/models/utils/forecaster.py
timecopilot/models/utils/gluonts_forecaster.py
timecopilot/models/utils/parallel_forecaster.py
timecopilot/utils/__init__.py
timecopilot/utils/experiment_handler.py
timecopilot-0.0.22.dist-info/METADATA
timecopilot-0.0.22.dist-info/WHEEL
timecopilot-0.0.22.dist-info/entry_points.txt
timecopilot-0.0.22.dist-info/licenses/LICENSE
timecopilot-0.0.22.dist-info/RECORD
