Metadata-Version: 2.4
Name: timecopilot
Version: 0.0.22
Summary: The GenAI Forecasting Agent · LLMs × Time Series Foundation Models
Author-email: Azul Garza <azul.garza.r@gmail.com>
License-Expression: MIT
License-File: LICENSE
Classifier: Development Status :: 2 - Pre-Alpha
Classifier: Intended Audience :: Developers
Classifier: Intended Audience :: Information Technology
Classifier: License :: OSI Approved :: MIT License
Classifier: Operating System :: OS Independent
Classifier: Programming Language :: Python
Classifier: Programming Language :: Python :: 3
Classifier: Programming Language :: Python :: 3 :: Only
Classifier: Programming Language :: Python :: 3.10
Classifier: Programming Language :: Python :: 3.11
Classifier: Programming Language :: Python :: 3.12
Classifier: Programming Language :: Python :: 3.13
Classifier: Topic :: Internet
Classifier: Topic :: Scientific/Engineering :: Artificial Intelligence
Classifier: Topic :: Software Development :: Libraries :: Python Modules
Requires-Python: >=3.10
Requires-Dist: fire
Requires-Dist: gluonts[torch]
Requires-Dist: huggingface-hub>=0.34.4
Requires-Dist: lightgbm>=4.6.0
Requires-Dist: logfire>=4.7.0
Requires-Dist: mlforecast>=1.0.2
Requires-Dist: neuralforecast>=3.0.2
Requires-Dist: nixtla>=0.6.6
Requires-Dist: openai>=1.99.7
Requires-Dist: pandas>=2.2.0; python_full_version >= '3.13'
Requires-Dist: prophet>=1.1.7
Requires-Dist: pydantic-ai>=0.7.0
Requires-Dist: scipy<=1.15.3
Requires-Dist: statsforecast
Requires-Dist: tabpfn-time-series==1.0.3; python_full_version < '3.13'
Requires-Dist: timecopilot-chronos-forecasting>=0.2.0
Requires-Dist: timecopilot-granite-tsfm>=0.1.1
Requires-Dist: timecopilot-timesfm>=0.2.1
Requires-Dist: timecopilot-tirex>=0.1.0; python_full_version >= '3.11'
Requires-Dist: timecopilot-toto>=0.1.3
Requires-Dist: timecopilot-uni2ts>=0.1.2; python_full_version < '3.14'
Requires-Dist: transformers<5,>=4.48; python_full_version >= '3.13'
Requires-Dist: transformers==4.40.1; python_full_version < '3.13'
Requires-Dist: tsfeatures
Requires-Dist: utilsforecast[plotting]
